{
    "info": {
        "added": 1640383610.770678, 
        "started": 1640397723.442676, 
        "duration": 611, 
        "ended": 1640398335.226974, 
        "owner": null, 
        "score": 0.0, 
        "id": 2548417, 
        "category": "file", 
        "git": {
            "head": "", 
            "fetch_head": ""
        }, 
        "monitor": null, 
        "package": "elf", 
        "route": "internet", 
        "custom": null, 
        "machine": {
            "status": "stopped", 
            "name": "Ubuntu1904x644", 
            "label": "Ubuntu1904x644", 
            "platform": "linux", 
            "manager": "VirtualBox", 
            "started_on": "2021-12-25 02:07:04", 
            "shutdown_on": "2021-12-25 02:12:14"
        }, 
        "platform": "linux", 
        "version": "2.0.7", 
        "options": "procmemdump=yes,route=internet"
    }, 
    "signatures": [], 
    "target": {
        "category": "file", 
        "file": {
            "mimetype": "application/x-object", 
            "yara": [], 
            "sha1": "0cbf215bcd6b552dc69cad531d3a10e563b4d665", 
            "name": "fou6.ko", 
            "type": "ELF 32-bit LSB relocatable, MIPS, MIPS32 rel2 version 1 (SYSV), BuildID[sha1]=e311c052be36b14b976b1c45cbff4235aee0d69e, not stripped", 
            "sha256": "68cf8c3c9254bf101a7417bf7e51a4fa205383f624cc82dd529edc628194556e", 
            "urls": [], 
            "crc32": "F06BA8DC", 
            "path": "/srv/cuckoo/cwd/storage/binaries/68cf8c3c9254bf101a7417bf7e51a4fa205383f624cc82dd529edc628194556e", 
            "ssdeep": null, 
            "size": 6940, 
            "sha512": "3477ef152b2f3ac9455fdbf38f6becad10cb58a0a8674b3a72ccf7613bd4fd206ecd3056871ce8ecb25c51cacb31f0466c0a75cee8b3f02b17d39cb947b03dda", 
            "md5": "0837e847e3d4af6e472cd7ae905179f9"
        }, 
        "custom": null
    }, 
    "irma": {
        "status": 0, 
        "probes_finished": 16, 
        "scan_id": "2cacc38b-162e-48cd-a44b-8485398d473c", 
        "parent_file_sha256": null, 
        "name": "68cf8c3c9254bf101a7417bf7e51a4fa205383f624cc82dd529edc628194556e", 
        "probes_total": 16, 
        "scan_date": 1640391136, 
        "other_results": [], 
        "submitter": "cli", 
        "file_infos": {
            "mimetype": "ELF 32-bit LSB relocatable, MIPS, MIPS32 rel2 version 1 (SYSV)", 
            "sha1": "0cbf215bcd6b552dc69cad531d3a10e563b4d665", 
            "tags": [], 
            "timestamp_first_scan": 1640391135.8, 
            "timestamp_last_scan": 1640391147.1, 
            "sha256": "68cf8c3c9254bf101a7417bf7e51a4fa205383f624cc82dd529edc628194556e", 
            "md5": "0837e847e3d4af6e472cd7ae905179f9", 
            "size": 6940
        }, 
        "probe_results": {
            "antivirus": {
                "Avast Core Security (Linux)": {
                    "status": 0, 
                    "duration": 0.0, 
                    "version": "3.0.3", 
                    "results": null, 
                    "virus_database_version": "unavailable"
                }, 
                "F-Secure Antivirus (Linux)": {
                    "status": 0, 
                    "duration": 0.02, 
                    "version": "11.10", 
                    "results": null, 
                    "virus_database_version": "2021-10-27_02"
                }, 
                "Windows Defender (Windows)": {
                    "status": 0, 
                    "duration": 0.05, 
                    "version": "1.1.18800.4", 
                    "results": null, 
                    "virus_database_version": "1.355.351.0"
                }, 
                "Comodo Antivirus (Linux)": {
                    "status": 0, 
                    "duration": 2.16, 
                    "version": "1.1.268025.1", 
                    "results": null, 
                    "virus_database_version": "2021-11-02"
                }, 
                "Kaspersky Antivirus (Win)": {
                    "status": 0, 
                    "duration": 3.32, 
                    "version": "21.3", 
                    "results": null, 
                    "virus_database_version": "2021-12-16 07:23:00 (full)"
                }, 
                "ESET NOD32 Antivirus (Linux)": {
                    "status": -1, 
                    "version": null, 
                    "error": "job error"
                }, 
                "GData (Windows)": {
                    "status": 0, 
                    "duration": 0.19, 
                    "version": "5.5.20197.1358", 
                    "results": null, 
                    "virus_database_version": "unavailable"
                }, 
                "Forticlient (Linux)": {
                    "status": 0, 
                    "duration": 3.04, 
                    "version": "unavailable", 
                    "results": null, 
                    "virus_database_version": "unavailable"
                }, 
                "Avira (Windows)": {
                    "status": 0, 
                    "duration": 4.0, 
                    "version": "8.3.64.66", 
                    "results": null, 
                    "virus_database_version": "8.19.1.122"
                }, 
                "eScan Antivirus (Linux)": {
                    "status": 0, 
                    "duration": 3.19, 
                    "version": "7.0.21", 
                    "results": null, 
                    "virus_database_version": "7.90035 (27/10/2021)"
                }, 
                "McAfee CLI scanner (Linux)": {
                    "status": 0, 
                    "duration": 6.07, 
                    "version": "6.0.6.653", 
                    "results": null, 
                    "virus_database_version": "10149"
                }, 
                "Sophos Anti-Virus (Linux)": {
                    "status": 0, 
                    "duration": 8.55, 
                    "version": "5.85.0", 
                    "results": null, 
                    "virus_database_version": "5.88 (26 October 2021)"
                }, 
                "DrWeb Antivirus (Linux)": {
                    "status": 0, 
                    "duration": 0.11, 
                    "version": "11.1.10.2108031732", 
                    "results": null, 
                    "virus_database_version": "unavailable"
                }, 
                "ClamAV (Linux)": {
                    "status": 0, 
                    "duration": 0.01, 
                    "version": "0.103.2", 
                    "results": null, 
                    "virus_database_version": "26334"
                }, 
                "Bitdefender Antivirus (Linux)": {
                    "status": 0, 
                    "duration": 6.79, 
                    "version": "7.90123", 
                    "results": null, 
                    "virus_database_version": null
                }, 
                "Emsisoft Commandline Scanner (Windows)": {
                    "status": 0, 
                    "duration": 0.23, 
                    "version": "2021.9.0.11172", 
                    "results": null, 
                    "virus_database_version": "unavailable"
                }
            }
        }, 
        "path": "", 
        "result_id": "26ec0e8d-5201-4790-bb4b-a8aa560b49fd", 
        "file_sha256": "68cf8c3c9254bf101a7417bf7e51a4fa205383f624cc82dd529edc628194556e"
    }, 
    "suricata": {
        "tls": [], 
        "files": [], 
        "alerts": [], 
        "http": []
    }, 
    "virustotal": {
        "summary": {
            "error": "resource has not been scanned yet"
        }
    }, 
    "network": {
        "tls": [], 
        "udp": [], 
        "dns_servers": [], 
        "http": [], 
        "icmp": [], 
        "smtp": [], 
        "tcp": [], 
        "smtp_ex": [], 
        "geoinfo": {}, 
        "mitm": [], 
        "hosts": [], 
        "pcap_sha256": "704e5e5b3234433c01fcfd1b20a306e77e985038120492dc53965c3edd38a4ea", 
        "dns": [], 
        "http_ex": [], 
        "domains": [], 
        "dead_hosts": [], 
        "irc": [], 
        "https_ex": []
    }, 
    "resubmit": {
        "resubmit_ids": []
    }, 
    "snort": {
        "alerts": []
    }, 
    "behavior": {
        "generic": [
            {
                "process_path": null, 
                "process_name": "sh", 
                "pid": 3845, 
                "summary": {}, 
                "first_seen": 1640383618.705298, 
                "ppid": -1
            }
        ], 
        "processes": [
            {
                "calls": [
                    {
                        "status": "ENOEXEC", 
                        "process_name": "sh", 
                        "pid": 3845, 
                        "raw": "Fri Dec 24 22:06:58 2021.705298 sh@7fa7ba4c4957[3845] execve(\"/tmp/fou6.ko\", [\"/tmp/fou6.ko\"], [\"SUDO_GID=0\", \"MAIL=/var/mail/root\", \"USER=root\", \"HOME=/root\", \"SUDO_UID=0\", \"LOGNAME=root\", \"SYSTEMTAP_MODULE=stap_\", \"TERM=unknown\", \"SYSTEMTAP_VERBOSE=2\", \"PATH=/usr/local/sbin:/usr/local/bin:/usr/sbin:/usr/bin:/sbin:/bin:/snap/bin\", \"DISPLAY=:0\", \"LANG=en_US.UTF-8\", \"XAUTHORITY=/root/.Xauthority\", \"SUDO_COMMAND=/usr/bin/staprun -vv -o stap.log /root/.cuckoo/stap_.ko -c sh -c /tmp/fou6.ko\", \"SHELL=/bin/bash\", \"SUDO_USER=root\", \"PWD=/tmp/tmpm2Ba_q\"]) = -8 (ENOEXEC)\n", 
                        "api": "execve", 
                        "return_value": "-8", 
                        "category": "process", 
                        "instruction_pointer": "7fa7ba4c4957", 
                        "arguments": {
                            "p2": [
                                "SUDO_GID=0", 
                                "MAIL=/var/mail/root", 
                                "USER=root", 
                                "HOME=/root", 
                                "SUDO_UID=0", 
                                "LOGNAME=root", 
                                "SYSTEMTAP_MODULE=stap_", 
                                "TERM=unknown", 
                                "SYSTEMTAP_VERBOSE=2", 
                                "PATH=/usr/local/sbin:/usr/local/bin:/usr/sbin:/usr/bin:/sbin:/bin:/snap/bin", 
                                "DISPLAY=:0", 
                                "LANG=en_US.UTF-8", 
                                "XAUTHORITY=/root/.Xauthority", 
                                "SUDO_COMMAND=/usr/bin/staprun -vv -o stap.log /root/.cuckoo/stap_.ko -c sh -c /tmp/fou6.ko", 
                                "SHELL=/bin/bash", 
                                "SUDO_USER=root", 
                                "PWD=/tmp/tmpm2Ba_q"
                            ], 
                            "p0": "/tmp/fou6.ko", 
                            "p1": [
                                "/tmp/fou6.ko"
                            ]
                        }, 
                        "time": 1640383618.705298
                    }, 
                    {
                        "status": "", 
                        "process_name": "sh", 
                        "pid": 3845, 
                        "raw": "Fri Dec 24 22:06:58 2021.722758 sh@7fa7ba4efcce[3845] openat(AT_FDCWD, \"/tmp/fou6.ko\", O_RDONLY|O_NOCTTY) = 3\n", 
                        "api": "openat", 
                        "return_value": "3", 
                        "category": "process", 
                        "instruction_pointer": "7fa7ba4efcce", 
                        "arguments": {
                            "p2": "O_RDONLY|O_NOCTTY", 
                            "p0": "AT_FDCWD", 
                            "p1": "/tmp/fou6.ko"
                        }, 
                        "time": 1640383618.722758
                    }, 
                    {
                        "status": "", 
                        "process_name": "sh", 
                        "pid": 3845, 
                        "raw": "Fri Dec 24 22:06:58 2021.722839 sh@7fa7ba4eff81[3845] read(3, 0x7ffd6d808e20, 128) = 128\n", 
                        "api": "read", 
                        "return_value": "128", 
                        "category": "process", 
                        "instruction_pointer": "7fa7ba4eff81", 
                        "arguments": {
                            "p2": "128", 
                            "p0": "3", 
                            "p1": "0x7ffd6d808e20"
                        }, 
                        "time": 1640383618.722839
                    }, 
                    {
                        "status": "", 
                        "process_name": "sh", 
                        "pid": 3845, 
                        "raw": "Fri Dec 24 22:06:58 2021.722898 sh@7fa7ba4f0674[3845] close(3) = 0\n", 
                        "api": "close", 
                        "return_value": "0", 
                        "category": "process", 
                        "instruction_pointer": "7fa7ba4f0674", 
                        "arguments": {
                            "p0": "3"
                        }, 
                        "time": 1640383618.722898
                    }, 
                    {
                        "status": "", 
                        "process_name": "sh", 
                        "pid": 3845, 
                        "raw": "Fri Dec 24 22:06:58 2021.723024 sh@7fa7ba4f0024[3845] write(2, \"sh: 1: \", 7) = 7\n", 
                        "api": "write", 
                        "return_value": "7", 
                        "category": "process", 
                        "instruction_pointer": "7fa7ba4f0024", 
                        "arguments": {
                            "p2": "7", 
                            "p0": "2", 
                            "p1": "sh: 1: "
                        }, 
                        "time": 1640383618.723024
                    }, 
                    {
                        "status": "", 
                        "process_name": "sh", 
                        "pid": 3845, 
                        "raw": "Fri Dec 24 22:06:58 2021.723090 sh@7fa7ba4f0024[3845] write(2, \"/tmp/fou6.ko: Exec format error\", 31) = 31\n", 
                        "api": "write", 
                        "return_value": "31", 
                        "category": "process", 
                        "instruction_pointer": "7fa7ba4f0024", 
                        "arguments": {
                            "p2": "31", 
                            "p0": "2", 
                            "p1": "/tmp/fou6.ko: Exec format error"
                        }, 
                        "time": 1640383618.72309
                    }, 
                    {
                        "status": "", 
                        "process_name": "sh", 
                        "pid": 3845, 
                        "raw": "Fri Dec 24 22:06:58 2021.723138 sh@7fa7ba4f0024[3845] write(2, \"\\n\", 1) = 1\n", 
                        "api": "write", 
                        "return_value": "1", 
                        "category": "process", 
                        "instruction_pointer": "7fa7ba4f0024", 
                        "arguments": {
                            "p2": "1", 
                            "p0": "2", 
                            "p1": "\n"
                        }, 
                        "time": 1640383618.723138
                    }, 
                    {
                        "status": "", 
                        "process_name": "sh", 
                        "pid": 3845, 
                        "raw": "Fri Dec 24 22:06:58 2021.723203 sh@7fa7ba4c4926[3845] exit_group(2)\n", 
                        "api": "exit_group", 
                        "return_value": "", 
                        "category": "process", 
                        "instruction_pointer": "7fa7ba4c4926", 
                        "arguments": {
                            "p0": "2"
                        }, 
                        "time": 1640383618.723203
                    }
                ], 
                "pid": 3845, 
                "process_name": "sh", 
                "command_line": "", 
                "first_seen": 1640383618.705298, 
                "ppid": -1, 
                "type": "process"
            }
        ], 
        "processtree": [
            {
                "track": true, 
                "pid": 3845, 
                "process_name": "sh", 
                "command_line": "", 
                "first_seen": 1640383618.705298, 
                "ppid": -1, 
                "children": []
            }
        ]
    }, 
    "debug": {
        "action": [], 
        "dbgview": [], 
        "errors": [], 
        "log": [
            "2021-12-24 22:06:50,003 [root] DEBUG: Starting analyzer from: /tmp/tmpm2Ba_q\n", 
            "2021-12-24 22:06:50,003 [root] DEBUG: Storing results at: /tmp/fBfUoXnEyc\n", 
            "2021-12-24 22:06:52,508 [modules.auxiliary.filecollector] INFO: FileCollector started v0.08\n", 
            "2021-12-24 22:06:52,511 [modules.auxiliary.human] INFO: Human started v0.02\n", 
            "2021-12-24 22:06:53,012 [modules.auxiliary.screenshots] INFO: Screenshots started v0.03\n", 
            "2021-12-24 22:06:58,704 [lib.core.packages] INFO: Process startup took 5.68 seconds\n", 
            "2021-12-24 22:06:58,705 [root] INFO: Added new process to list with pid: 3838\n", 
            "2021-12-24 22:07:04,786 [root] INFO: Process with pid 3838 has terminated\n", 
            "2021-12-24 22:07:04,787 [root] INFO: Process list is empty, terminating analysis.\n", 
            "2021-12-24 22:07:07,796 [lib.core.packages] INFO: Package requested stop\n", 
            "2021-12-24 22:07:07,797 [lib.core.packages] WARNING: Exception uploading log: [Errno 3] No such process\n", 
            "2021-12-24 22:10:44,378 [root] INFO: Terminating remaining processes before shutdown.\n", 
            "2021-12-24 22:10:44,378 [root] INFO: Analysis completed.\n"
        ], 
        "cuckoo": [
            "2021-12-25 02:02:03,859 [cuckoo.core.scheduler] DEBUG: Task #2548417: no machine available yet\n", 
            "2021-12-25 02:02:33,902 [cuckoo.core.scheduler] DEBUG: Task #2548417: no machine available yet\n", 
            "2021-12-25 02:03:03,947 [cuckoo.core.scheduler] DEBUG: Task #2548417: no machine available yet\n", 
            "2021-12-25 02:03:33,988 [cuckoo.core.scheduler] DEBUG: Task #2548417: no machine available yet\n", 
            "2021-12-25 02:04:04,105 [cuckoo.core.scheduler] DEBUG: Task #2548417: no machine available yet\n", 
            "2021-12-25 02:04:34,147 [cuckoo.core.scheduler] DEBUG: Task #2548417: no machine available yet\n", 
            "2021-12-25 02:05:04,188 [cuckoo.core.scheduler] DEBUG: Task #2548417: no machine available yet\n", 
            "2021-12-25 02:05:34,231 [cuckoo.core.scheduler] DEBUG: Task #2548417: no machine available yet\n", 
            "2021-12-25 02:06:04,278 [cuckoo.core.scheduler] DEBUG: Task #2548417: no machine available yet\n", 
            "2021-12-25 02:06:34,326 [cuckoo.core.scheduler] DEBUG: Task #2548417: no machine available yet\n", 
            "2021-12-25 02:07:04,375 [cuckoo.core.scheduler] INFO: Task #2548417: acquired machine Ubuntu1904x644 (label=Ubuntu1904x644)\n", 
            "2021-12-25 02:07:04,375 [cuckoo.core.resultserver] DEBUG: Now tracking machine 192.168.168.104 for task #2548417\n", 
            "2021-12-25 02:07:04,550 [cuckoo.auxiliary.sniffer] INFO: Started sniffer with PID 3080595 (interface=vboxnet0, host=192.168.168.104)\n", 
            "2021-12-25 02:07:04,725 [cuckoo.machinery.virtualbox] DEBUG: Starting vm Ubuntu1904x644\n", 
            "2021-12-25 02:07:05,168 [cuckoo.machinery.virtualbox] DEBUG: Restoring virtual machine Ubuntu1904x644 to Snapshot\n", 
            "2021-12-25 02:07:44,122 [cuckoo.core.guest] INFO: Starting analysis #2548417 on guest (id=Ubuntu1904x644, ip=192.168.168.104)\n", 
            "2021-12-25 02:07:45,127 [cuckoo.core.guest] DEBUG: Ubuntu1904x644: not ready yet\n", 
            "2021-12-25 02:07:50,149 [cuckoo.core.guest] INFO: Guest is running Cuckoo Agent 0.10 (id=Ubuntu1904x644, ip=192.168.168.104)\n", 
            "2021-12-25 02:07:50,164 [cuckoo.core.guest] DEBUG: Uploading analyzer to guest (id=Ubuntu1904x644, ip=192.168.168.104, monitor=latest, size=72028)\n", 
            "2021-12-25 02:07:50,313 [cuckoo.core.resultserver] DEBUG: Task #2548417: live log analysis.log initialized.\n", 
            "2021-12-25 02:08:01,119 [cuckoo.core.resultserver] DEBUG: Task #2548417: File upload for 'shots/0001.jpg'\n", 
            "2021-12-25 02:08:01,151 [cuckoo.core.resultserver] DEBUG: Task #2548417 uploaded file length: 171563\n", 
            "2021-12-25 02:08:05,294 [cuckoo.core.guest] DEBUG: Ubuntu1904x644: analysis #2548417 still processing\n", 
            "2021-12-25 02:08:08,123 [cuckoo.core.resultserver] DEBUG: Task #2548417: File upload for 'logs/all.stap'\n", 
            "2021-12-25 02:08:08,126 [cuckoo.core.resultserver] DEBUG: Task #2548417 uploaded file length: 1167\n", 
            "2021-12-25 02:08:20,355 [cuckoo.core.guest] DEBUG: Ubuntu1904x644: analysis #2548417 still processing\n", 
            "2021-12-25 02:08:35,513 [cuckoo.core.guest] DEBUG: Ubuntu1904x644: analysis #2548417 still processing\n", 
            "2021-12-25 02:08:50,641 [cuckoo.core.guest] DEBUG: Ubuntu1904x644: analysis #2548417 still processing\n", 
            "2021-12-25 02:09:05,746 [cuckoo.core.guest] DEBUG: Ubuntu1904x644: analysis #2548417 still processing\n", 
            "2021-12-25 02:09:20,854 [cuckoo.core.guest] DEBUG: Ubuntu1904x644: analysis #2548417 still processing\n", 
            "2021-12-25 02:09:36,005 [cuckoo.core.guest] DEBUG: Ubuntu1904x644: analysis #2548417 still processing\n", 
            "2021-12-25 02:09:51,107 [cuckoo.core.guest] DEBUG: Ubuntu1904x644: analysis #2548417 still processing\n", 
            "2021-12-25 02:10:06,236 [cuckoo.core.guest] DEBUG: Ubuntu1904x644: analysis #2548417 still processing\n", 
            "2021-12-25 02:10:21,296 [cuckoo.core.guest] DEBUG: Ubuntu1904x644: analysis #2548417 still processing\n", 
            "2021-12-25 02:10:36,357 [cuckoo.core.guest] DEBUG: Ubuntu1904x644: analysis #2548417 still processing\n", 
            "2021-12-25 02:10:51,418 [cuckoo.core.guest] DEBUG: Ubuntu1904x644: analysis #2548417 still processing\n", 
            "2021-12-25 02:11:06,476 [cuckoo.core.guest] DEBUG: Ubuntu1904x644: analysis #2548417 still processing\n", 
            "2021-12-25 02:11:21,545 [cuckoo.core.guest] DEBUG: Ubuntu1904x644: analysis #2548417 still processing\n", 
            "2021-12-25 02:11:36,621 [cuckoo.core.guest] DEBUG: Ubuntu1904x644: analysis #2548417 still processing\n", 
            "2021-12-25 02:11:45,652 [cuckoo.core.guest] INFO: Ubuntu1904x644: analysis completed successfully\n", 
            "2021-12-25 02:11:45,662 [cuckoo.core.plugins] DEBUG: Stopped auxiliary module: Redsocks\n", 
            "2021-12-25 02:11:45,784 [cuckoo.core.plugins] DEBUG: Stopped auxiliary module: Sniffer\n", 
            "2021-12-25 02:11:59,583 [cuckoo.machinery.virtualbox] INFO: Successfully generated memory dump for virtual machine with label Ubuntu1904x644 to path /srv/cuckoo/cwd/storage/analyses/2548417/memory.dmp\n", 
            "2021-12-25 02:11:59,584 [cuckoo.machinery.virtualbox] DEBUG: Stopping vm Ubuntu1904x644\n", 
            "2021-12-25 02:12:14,832 [cuckoo.core.resultserver] DEBUG: Stopped tracking machine 192.168.168.104 for task #2548417\n", 
            "2021-12-25 02:12:14,982 [cuckoo.core.scheduler] DEBUG: Released database task #2548417\n", 
            "2021-12-25 02:12:15,104 [cuckoo.core.scheduler] INFO: Task #2548417: analysis procedure completed\n"
        ]
    }, 
    "strings": [
        "3can't add fou6 ops", 
        "3can't add gue6 ops", 
        "license=GPL", 
        "author=Tom Herbert <therbert@google.com>", 
        "depends=fou,ip6_tunnel", 
        "intree=Y", 
        "vermagic=4.9.0-13-4kc-malta mod_unload modversions MIPS32_R2 32BIT ", 
        "gue6_build_header", 
        "fou6_build_header", 
        "4Fmodule_layout", 
        "_mcount", 
        "+#udp6_set_csum", 
        "__gue_build_header", 
        "fou_encap_hlen", 
        "'printk", 
        "\u001f__fou_build_header", 
        "skb_push", 
        "ip6_tnl_encap_add_ops", 
        "__stack_chk_fail", 
        "__stack_chk_guard", 
        "gue_encap_hlen", 
        "ip6_tnl_encap_del_ops", 
        "GCC: (Debian 6.3.0-18+deb9u1) 6.3.0 20170516", 
        "GCC: (Debian 6.3.0-18+deb9u1) 6.3.0 20170516", 
        "fou6.ko", 
        "fou6_build_udp", 
        "fou6_init", 
        "fou_ip6tun_ops", 
        "gue_ip6tun_ops", 
        "fou6_fini", 
        "__UNIQUE_ID_license162", 
        "__UNIQUE_ID_author161", 
        "__ksymtab_gue6_build_header", 
        "__kstrtab_gue6_build_header", 
        "__kcrctab_gue6_build_header", 
        "__ksymtab_fou6_build_header", 
        "__kstrtab_fou6_build_header", 
        "__kcrctab_fou6_build_header", 
        "__module_depends", 
        "____versions", 
        "__UNIQUE_ID_intree53", 
        "__UNIQUE_ID_vermagic52", 
        "ip6_tnl_encap_del_ops", 
        "__this_module", 
        "gue_encap_hlen", 
        "__stack_chk_guard", 
        "cleanup_module", 
        "init_module", 
        "__stack_chk_fail", 
        "ip6_tnl_encap_add_ops", 
        "skb_push", 
        "__fou_build_header", 
        "printk", 
        "fou_encap_hlen", 
        "__crc_gue6_build_header", 
        "__gue_build_header", 
        "__crc_fou6_build_header", 
        "udp6_set_csum", 
        "_mcount", 
        ".symtab", 
        ".strtab", 
        ".shstrtab", 
        ".note.gnu.build-id", 
        ".rel.text", 
        ".rel.init.text", 
        ".rel.exit.text", 
        ".rel__ksymtab", 
        ".rel__kcrctab", 
        ".reginfo", 
        ".MIPS.abiflags", 
        ".rodata.str1.4", 
        ".modinfo", 
        ".rel.rodata", 
        "__ksymtab_strings", 
        ".rel__mcount_loc", 
        "__versions", 
        ".rel.gnu.linkonce.this_module", 
        ".rel.pdr", 
        ".mdebug.abi32", 
        ".comment", 
        ".gnu.attributes", 
        ".gnu_debuglink"
    ], 
    "metadata": {
        "output": {
            "pcap": {
                "basename": "dump.pcap", 
                "sha256": "704e5e5b3234433c01fcfd1b20a306e77e985038120492dc53965c3edd38a4ea", 
                "dirname": ""
            }
        }
    }
}